ofxstatement_be_triodos-0.0.1-py3.5-nspkg.pth
ofxstatement/plugins/triodosbe.py
ofxstatement_be_triodos-0.0.1.dist-info/DESCRIPTION.rst
ofxstatement_be_triodos-0.0.1.dist-info/METADATA
ofxstatement_be_triodos-0.0.1.dist-info/RECORD
ofxstatement_be_triodos-0.0.1.dist-info/WHEEL
ofxstatement_be_triodos-0.0.1.dist-info/entry_points.txt
ofxstatement_be_triodos-0.0.1.dist-info/metadata.json
ofxstatement_be_triodos-0.0.1.dist-info/namespace_packages.txt
ofxstatement_be_triodos-0.0.1.dist-info/top_level.txt
ofxstatement_be_triodos-0.0.1.dist-info/zip-safe
