Metadata-Version: 2.0
Name: ofxstatement-be-triodos
Version: 0.0.1
Summary: ofxstatement plugin for parsing Belgian Triodos bank's CSV statements to OFX
Home-page: https://github.com/renardeau/ofxstatement-be-triodos
Author: Bernard Butaye
Author-email: UNKNOWN
License: GPLv3
Keywords: ofx,banking,statement,triodos,csv
Platform: UNKNOWN
Classifier: Development Status :: 3 - Alpha
Classifier: Programming Language :: Python :: 3
Classifier: Natural Language :: English
Classifier: Topic :: Office/Business :: Financial :: Accounting
Classifier: Topic :: Utilities
Classifier: Environment :: Console
Classifier: Operating System :: OS Independent
Classifier: License :: OSI Approved :: GNU General Public License v3 (GPLv3)
Requires-Dist: ofxstatement
